acmetric/__init__.py
acmetric/configuration/base/eda/cs_parameters.yaml
acmetric/configuration/base/eda/ts_parameters.yaml
acmetric/configuration/base/logger.yaml
acmetric/configuration/local/.gitkeep
acmetric/data/README.md
acmetric/data/__init__.py
acmetric/data/abs.py
acmetric/data/catalog.py
acmetric/data/catalogs/__init__.py
acmetric/data/catalogs/kedro/__init__.py
acmetric/data/catalogs/kedro/kedro_catalog.py
acmetric/data/catalogs/kedro/kedro_configs.py
acmetric/data/catalogs/kedro/tests/__init__.py
acmetric/data/catalogs/kedro/tests/test_kedro_catalog.py
acmetric/data/catalogs/kedro/tests/test_kedro_configs.py
acmetric/data/default_attributes.py
acmetric/data/tests/__init__.py
acmetric/data/tests/test_catalog.py
acmetric/data/tests/test_default_attributes.py
acmetric/data/validators/__init__.py
acmetric/data/validators/gx/__init__.py
acmetric/data/validators/gx/batch_managers/__init__.py
acmetric/data/validators/gx/batch_managers/batch_manager.py
acmetric/data/validators/gx/batch_managers/batch_validation.py
acmetric/data/validators/gx/batch_managers/checkpoint_manager.py
acmetric/data/validators/gx/batch_managers/datasource_manager.py
acmetric/data/validators/gx/batch_managers/expectation_addition/__init__.py
acmetric/data/validators/gx/batch_managers/expectation_addition/base.py
acmetric/data/validators/gx/batch_managers/expectation_addition/configuration_based.py
acmetric/data/validators/gx/batch_managers/expectation_addition/parse_expectations_dict.py
acmetric/data/validators/gx/batch_managers/expectation_addition/tests/__init__.py
acmetric/data/validators/gx/batch_managers/expectation_addition/tests/test_configuration_based.py
acmetric/data/validators/gx/batch_managers/expectation_addition/tests/test_parse_expectations_dict.py
acmetric/data/validators/gx/batch_managers/expectation_addition/tests/test_validator_based.py
acmetric/data/validators/gx/batch_managers/expectation_addition/validator_based.py
acmetric-2.0.11.dist-info/METADATA
acmetric-2.0.11.dist-info/WHEEL
acmetric-2.0.11.dist-info/entry_points.txt
acmetric-2.0.11.dist-info/RECORD
