Metadata-Version: 2.1
Name: acmetric
Version: 2.0.11
Summary: acmetric package and sample project.
Author: Ivan
Author-email: ivan@acmetric.org
Requires-Python: >=3.9
Classifier: Programming Language :: Python :: 3
Classifier: Programming Language :: Python :: 3.9
Classifier: Programming Language :: Python :: 3.10
Classifier: Programming Language :: Python :: 3.11
Classifier: Programming Language :: Python :: 3.12
Classifier: Programming Language :: Python :: 3.13
Provides-Extra: gcp
Provides-Extra: great-expectations
Provides-Extra: kedro
Provides-Extra: logging
Provides-Extra: pandera
Provides-Extra: spark
Requires-Dist: dbt-bigquery (>=1.0.0,<2.0.0) ; extra == "gcp"
Requires-Dist: fastparquet (>=2023.7.0,<2024.0.0)
Requires-Dist: gcsfs (>=2023.9.2,<2024.0.0) ; extra == "gcp"
Requires-Dist: google-api-core (>=2.8.2,<3.0.0) ; extra == "gcp"
Requires-Dist: google-cloud-bigquery-storage (>=2.13.2,<3.0.0) ; extra == "gcp"
Requires-Dist: great-expectations (>=0.18.2,<0.19.0) ; extra == "great-expectations"
Requires-Dist: hydra-core (>=1.2.0,<2.0.0)
Requires-Dist: kedro (>=0.18.13,<0.19.0) ; extra == "kedro"
Requires-Dist: kedro-datasets (>=1.7.0,<2.0.0) ; extra == "kedro"
Requires-Dist: loguru (>=0.7.2,<0.8.0) ; extra == "logging"
Requires-Dist: matplotlib (>=3.7.2,<4.0.0)
Requires-Dist: numpy (>=1.23.0,<2.0.0)
Requires-Dist: pandas (>=1.4.3,<2.0.0)
Requires-Dist: pandas-gbq (>=0.19.2,<0.20.0) ; extra == "gcp"
Requires-Dist: pandera (>=0.17.2,<0.18.0) ; extra == "pandera"
Requires-Dist: pyarrow (>=12.0.1,<13.0.0)
Requires-Dist: pydantic
Requires-Dist: pyspark (>=3.2.0,<4.0.0) ; extra == "spark"
Requires-Dist: scipy (>=1.8.1,<2.0.0)
Requires-Dist: seaborn (>=0.11.2,<0.12.0)
Requires-Dist: statsmodels (>=0.14.4,<0.15.0)
